odoo8_addon_geoengine_partner-8.0.0.1.0.99.dev11-py2.7-nspkg.pth
odoo_addons/geoengine_partner/__openerp__.py
odoo_addons/geoengine_partner/geo_partner_view.xml
odoo_addons/geoengine_partner/geo_partner.py
odoo_addons/geoengine_partner/__init__.py
odoo_addons/geoengine_partner/README.rst
odoo_addons/geoengine_partner/i18n/ja.po
odoo_addons/geoengine_partner/i18n/lv.po
odoo_addons/geoengine_partner/i18n/zh_CN.po
odoo_addons/geoengine_partner/i18n/nb_NO.po
odoo_addons/geoengine_partner/i18n/tr_TR.po
odoo_addons/geoengine_partner/i18n/ru.po
odoo_addons/geoengine_partner/i18n/pt.po
odoo_addons/geoengine_partner/i18n/fr_CH.po
odoo_addons/geoengine_partner/i18n/it.po
odoo_addons/geoengine_partner/i18n/es.po
odoo_addons/geoengine_partner/i18n/nl_BE.po
odoo_addons/geoengine_partner/i18n/ar.po
odoo_addons/geoengine_partner/i18n/lt.po
odoo_addons/geoengine_partner/i18n/ro.po
odoo_addons/geoengine_partner/i18n/tr.po
odoo_addons/geoengine_partner/i18n/mk.po
odoo_addons/geoengine_partner/i18n/hr.po
odoo_addons/geoengine_partner/i18n/bg.po
odoo_addons/geoengine_partner/i18n/es_EC.po
odoo_addons/geoengine_partner/i18n/zh_TW.po
odoo_addons/geoengine_partner/i18n/hu.po
odoo_addons/geoengine_partner/i18n/fr_CA.po
odoo_addons/geoengine_partner/i18n/gl.po
odoo_addons/geoengine_partner/i18n/ca.po
odoo_addons/geoengine_partner/i18n/es_CR.po
odoo_addons/geoengine_partner/i18n/sl.po
odoo_addons/geoengine_partner/i18n/sr@latin.po
odoo_addons/geoengine_partner/i18n/th.po
odoo_addons/geoengine_partner/i18n/cs.po
odoo_addons/geoengine_partner/i18n/pt_PT.po
odoo_addons/geoengine_partner/i18n/eu.po
odoo_addons/geoengine_partner/i18n/nb.po
odoo_addons/geoengine_partner/i18n/da.po
odoo_addons/geoengine_partner/i18n/et.po
odoo_addons/geoengine_partner/i18n/mn.po
odoo_addons/geoengine_partner/i18n/nl.po
odoo_addons/geoengine_partner/i18n/am.po
odoo_addons/geoengine_partner/i18n/de.po
odoo_addons/geoengine_partner/i18n/vi.po
odoo8_addon_geoengine_partner-8.0.0.1.0.99.dev11.dist-info/top_level.txt
odoo8_addon_geoengine_partner-8.0.0.1.0.99.dev11.dist-info/WHEEL
odoo8_addon_geoengine_partner-8.0.0.1.0.99.dev11.dist-info/RECORD
odoo8_addon_geoengine_partner-8.0.0.1.0.99.dev11.dist-info/metadata.json
odoo8_addon_geoengine_partner-8.0.0.1.0.99.dev11.dist-info/DESCRIPTION.rst
odoo8_addon_geoengine_partner-8.0.0.1.0.99.dev11.dist-info/METADATA
odoo8_addon_geoengine_partner-8.0.0.1.0.99.dev11.dist-info/namespace_packages.txt
